odoo/addons/stock_request_submit/README.rst
odoo/addons/stock_request_submit/__init__.py
odoo/addons/stock_request_submit/__manifest__.py
odoo/addons/stock_request_submit/uninstall_hook.py
odoo/addons/stock_request_submit/i18n/es.po
odoo/addons/stock_request_submit/i18n/stock_request_submit.pot
odoo/addons/stock_request_submit/i18n/zh_CN.po
odoo/addons/stock_request_submit/models/__init__.py
odoo/addons/stock_request_submit/models/stock_request.py
odoo/addons/stock_request_submit/models/stock_request_order.py
odoo/addons/stock_request_submit/readme/CONTRIBUTORS.rst
odoo/addons/stock_request_submit/readme/DESCRIPTION.rst
odoo/addons/stock_request_submit/static/description/icon.png
odoo/addons/stock_request_submit/static/description/index.html
odoo/addons/stock_request_submit/tests/__init__.py
odoo/addons/stock_request_submit/tests/test_stock_request_submit.py
odoo/addons/stock_request_submit/views/stock_request_order_views.xml
odoo/addons/stock_request_submit/views/stock_request_views.xml
odoo13_addon_stock_request_submit-13.0.1.0.1.dev4.dist-info/METADATA
odoo13_addon_stock_request_submit-13.0.1.0.1.dev4.dist-info/WHEEL
odoo13_addon_stock_request_submit-13.0.1.0.1.dev4.dist-info/top_level.txt
odoo13_addon_stock_request_submit-13.0.1.0.1.dev4.dist-info/RECORD
